{
    "origin": "Florence",
    "destination": "Lille",
    "alternatives": [
        {
            "type": "rail",
            "legs": [
                {
                    "start": {
                        "name": "FIRENZE S.M.N. (Italy)",
                        "lat": 43.776667,
                        "lon": 11.247501
                    },
                    "end": {
                        "name": "MILANO CENTRALE (Italy)",
                        "lat": 45.486388,
                        "lon": 9.204163
                    },
                    "time_s": 7680.0
                },
                {
                    "start": {
                        "name": "MILANO CENTRALE (Italy)",
                        "lat": 45.486388,
                        "lon": 9.204163
                    },
                    "end": {
                        "name": "BASEL SBB (Switzerland)",
                        "lat": 47.547498,
                        "lon": 7.58944
                    },
                    "time_s": 15120.0
                },
                {
                    "start": {
                        "name": "BASEL SBB (Switzerland)",
                        "lat": 47.547498,
                        "lon": 7.58944
                    },
                    "end": {
                        "name": "PARIS GARE DE LYON (France)",
                        "lat": 48.845001,
                        "lon": 2.373611
                    },
                    "time_s": 11220.0
                },
                {
                    "start": {
                        "name": "PARIS GARE DE LYON (France)",
                        "lat": 48.845001,
                        "lon": 2.373611
                    },
                    "end": {
                        "name": "PARIS NORD (France)",
                        "lat": 48.880275,
                        "lon": 2.355282
                    },
                    "time_s": 2400.0
                },
                {
                    "start": {
                        "name": "PARIS NORD (France)",
                        "lat": 48.880275,
                        "lon": 2.355282
                    },
                    "end": {
                        "name": "LILLE EUROPE (France)",
                        "lat": 50.639446,
                        "lon": 3.07556
                    },
                    "time_s": 4560.0
                }
            ],
            "total_duration_s": 45660.0,
            "total_distance_km": 1128.9270274884182
        },
        {
            "type": "air",
            "legs": [
                {
                    "start": {
                        "name": "FLR"
                    },
                    "end": {
                        "name": "CDG"
                    },
                    "aircraft": "319",
                    "distance": 879.3473737244514
                },
                {
                    "start": {
                        "name": "CDG"
                    },
                    "end": {
                        "name": "LYS"
                    },
                    "aircraft": "321",
                    "distance": 412.18284884671124
                },
                {
                    "start": {
                        "name": "LYS"
                    },
                    "end": {
                        "name": "LIL"
                    },
                    "aircraft": "E70",
                    "distance": 557.858500923973
                }
            ],
            "total_duration_s": "PT10H30M",
            "total_distance_km": 1849.3887234951355
        }
    ]
}