{
    "origin": "Amsterdam",
    "destination": "Munich",
    "alternatives": [
        {
            "type": "rail",
            "legs": [
                {
                    "start": {
                        "name": "AMSTERDAM CENTRAAL (Netherlands)",
                        "lat": 52.378607,
                        "lon": 4.900829
                    },
                    "end": {
                        "name": "DUESSELDORF HBF (Germany)",
                        "lat": 51.219996,
                        "lon": 6.794443
                    },
                    "time_s": 9720.0
                },
                {
                    "start": {
                        "name": "DUESSELDORF HBF (Germany)",
                        "lat": 51.219996,
                        "lon": 6.794443
                    },
                    "end": {
                        "name": "FRANKFURT(M) FLUGHAFEN FERNBF (Germany)",
                        "lat": 50.053052,
                        "lon": 8.57028
                    },
                    "time_s": 5100.0
                },
                {
                    "start": {
                        "name": "FRANKFURT(M) FLUGHAFEN FERNBF (Germany)",
                        "lat": 50.053052,
                        "lon": 8.57028
                    },
                    "end": {
                        "name": "MUENCHEN HBF (Germany)",
                        "lat": 48.140274,
                        "lon": 11.55833
                    },
                    "time_s": 12960.0
                }
            ],
            "total_duration_s": 30000.0,
            "total_distance_km": 667.6974009663427
        },
        {
            "type": "air",
            "legs": [
                {
                    "start": {
                        "name": "AMS"
                    },
                    "end": {
                        "name": "MUC"
                    },
                    "aircraft": "319",
                    "distance": 664.1671918724076
                }
            ],
            "total_duration_s": "PT1H25M",
            "total_distance_km": 664.1671918724076
        }
    ]
}