{
    "origin": "Florence",
    "destination": "Cologne",
    "alternatives": [
        {
            "type": "rail",
            "legs": [
                {
                    "start": {
                        "name": "FIRENZE S.M.N. (Italy)",
                        "lat": 43.776667,
                        "lon": 11.247501
                    },
                    "end": {
                        "name": "MILANO CENTRALE (Italy)",
                        "lat": 45.486388,
                        "lon": 9.204163
                    },
                    "time_s": 7680.0
                },
                {
                    "start": {
                        "name": "MILANO CENTRALE (Italy)",
                        "lat": 45.486388,
                        "lon": 9.204163
                    },
                    "end": {
                        "name": "MANNHEIM HBF (Germany)",
                        "lat": 49.479442,
                        "lon": 8.46889
                    },
                    "time_s": 23880.0
                },
                {
                    "start": {
                        "name": "MANNHEIM HBF (Germany)",
                        "lat": 49.479442,
                        "lon": 8.46889
                    },
                    "end": {
                        "name": "KOELN HBF (Germany)",
                        "lat": 50.943056,
                        "lon": 6.958613
                    },
                    "time_s": 5340.0
                }
            ],
            "total_duration_s": 40080.0,
            "total_distance_km": 892.001817380854
        },
        {
            "type": "air",
            "legs": [
                {
                    "start": {
                        "name": "FLR"
                    },
                    "end": {
                        "name": "VIE"
                    },
                    "aircraft": "E95",
                    "distance": 632.6121715947314
                },
                {
                    "start": {
                        "name": "VIE"
                    },
                    "end": {
                        "name": "CGN"
                    },
                    "aircraft": "320",
                    "distance": 745.9899815657448
                }
            ],
            "total_duration_s": "PT9H15M",
            "total_distance_km": 1378.602153160476
        }
    ]
}